{
  "resourceType": "Practitioner",
  "id": "Practitioner-3",
  "meta": {
    "lastUpdated": "2024-12-09T23:18:00.365+00:00"
  },
  "extension": [
    {
      "url": "https://example.org/fhir/StructureDefinition/Sex",
      "valueCode": "Male"
    }
  ],
  "identifier": [
    {
      "use": "PRC",
      "value": "12345"
    }
  ],
  "name": [
    {
      "extension": [
        {
          "url": "https://example.org/fhir/StructureDefinition/MiddleName",
          "valueString": "Rizal"
        }
      ],
      "use": "official",
      "family": "Dela Cruz",
      "given": [
        "Juan",
        "Pedro",
        "Santos"
      ]
    }
  ],
  "telecom": [
    {
      "system": "phone",
      "value": "(03) 5555 6473"
    },
    {
      "system": "phone",
      "value": "(0939) 929 3814",
      "use": "mobile"
    }
  ]
}